Workbook

Sheet 参数设置
A1: 定价分析参数配置
A3: 目标净利率 (%) | B3: 30
A4: 变动成本率 (%) | B4: 25
A5: 支付手续费 (%) | B5: 2.9
A6: 支付固定费 ($) | B6: 0.3
A7: Shopify交易费 (%) | B7: 1
A8: 广告CPA摊销 (%) | B8: 18
A9: 退货率 (%) | B9: 3
A10: 包装赠品 (%) | B10: 1.5
A12: 划线价倍率 | B12: 1.4
A13: 价格差额比例 (%) | B13: 30
A15: 物流费用基准
A16: 小件 (< $10) | B16: 6.44
A17: 中件 ($10-$25) | B17: 8.97
A18: 大件 (>$25) | B18: 15
A20: 关税规则
A21: US <$800 免税阈值 | B21: 800
A22: 小包关税 (%) | B22: 0
A23: 大件关税 (%) | B23: 10

Sheet 产品定价分析表_2026-05-07
A1: 产品ID | B1: 产品名称 | C1: SKU编码 | D1: 产品分类 | E1: 变体数量 | F1: 库存状态 | G1: CJ采购价($) | H1: 头程运费($) | I1: 关税($) | J1: 包装成本($) | K1: 落地成本($) | L1: 目标净利率(%) | M1: 变动成本率(%) | N1: 计算零售价($) | O1: 心理定价($) | P1: 亚马逊均价($) | Q1: 价格竞争力 | R1: 划线价格($) | S1: 折扣率(%) | T1: 毛利率(%) | U1: 净利率(%) | V1: 数据匹配状态
A2: SHOP-00001 | B2: 超声波宠物除毛刷 V1 | C2: PET-宠物-0001 | D2: 宠物美容 | E2: 2 | F2: 缺货 | G2: 43.58 | H2: 15 | I2: 0 | J2: 0 | K2: =G2+H2+I2+J2 | L2: =$B$3 | M2: =$B$4 | N2: =K2/(1-(L2+M2)) | O2: =ROUND(K2/(1-(L2+M2)),2) | P2: 142.17 | Q2: =IF(N2<P2,"低于亚马逊",IF(N2<P2*1.1,"接近亚马逊","高于亚马逊")) | R2: =ROUND(N2*$B$12,2) | S2: =(O2-N2)/O2 | T2: =(N2-K2)/N2 | U2: =(N2-K2)/N2-$B$4 | V2: 已匹配
A3: SHOP-00002 | B3: 智能宠物饮水机 V1 | C3: PET-宠物-0002 | D3: 宠物玩具 | E3: 1 | F3: 有货 | G3: 27.4 | H3: 15 | I3: 0 | J3: 0 | K3: =G3+H3+I3+J3 | L3: =$B$3 | M3: =$B$4 | N3: =K3/(1-(L3+M3)) | O3: =ROUND(K3/(1-(L3+M3)),2) | P3: 77.85 | Q3: =IF(N3<P3,"低于亚马逊",IF(N3<P3*1.1,"接近亚马逊","高于亚马逊")) | R3: =ROUND(N3*$B$12,2) | S3: =(O3-N3)/O3 | T3: =(N3-K3)/N3 | U3: =(N3-K3)/N3-$B$4 | V3: 已匹配
A4: SHOP-00003 | B4: 宠物便携折叠笼 V1 | C4: PET-宠物-0003 | D4: 宠物喂食 | E4: 3 | F4: 有货 | G4: 24 | H4: 8.97 | I4: 0 | J4: 0 | K4: =G4+H4+I4+J4 | L4: =$B$3 | M4: =$B$4 | N4: =K4/(1-(L4+M4)) | O4: =ROUND(K4/(1-(L4+M4)),2) | P4: 56.26 | Q4: =IF(N4<P4,"低于亚马逊",IF(N4<P4*1.1,"接近亚马逊","高于亚马逊")) | R4: =ROUND(N4*$B$12,2) | S4: =(O4-N4)/O4 | T4: =(N4-K4)/N4 | U4: =(N4-K4)/N4-$B$4 | V4: 已匹配
A5: SHOP-00004 | B5: 宠物多功能护理包 V1 | C5: PET-宠物-0004 | D5: 宠物出行 | E5: 1 | F5: 有货 | G5: 29.79 | H5: 15 | I5: 0 | J5: 0 | K5: =G5+H5+I5+J5 | L5: =$B$3 | M5: =$B$4 | N5: =K5/(1-(L5+M5)) | O5: =ROUND(K5/(1-(L5+M5)),2) | P5: 91.11 | Q5: =IF(N5<P5,"低于亚马逊",IF(N5<P5*1.1,"接近亚马逊","高于亚马逊")) | R5: =ROUND(N5*$B$12,2) | S5: =(O5-N5)/O5 | T5: =(N5-K5)/N5 | U5: =(N5-K5)/N5-$B$4 | V5: 已匹配
A6: SHOP-00005 | B6: 宠物GPS定位项圈 V1 | C6: PET-宠物-0005 | D6: 宠物清洁 | E6: 4 | F6: 库存紧张 | G6: 16.91 | H6: 8.97 | I6: 0 | J6: 0 | K6: =G6+H6+I6+J6 | L6: =$B$3 | M6: =$B$4 | N6: =K6/(1-(L6+M6)) | O6: =ROUND(K6/(1-(L6+M6)),2) | P6: 40.51 | Q6: =IF(N6<P6,"低于亚马逊",IF(N6<P6*1.1,"接近亚马逊","高于亚马逊")) | R6: =ROUND(N6*$B$12,2) | S6: =(O6-N6)/O6 | T6: =(N6-K6)/N6 | U6: =(N6-K6)/N6-$B$4 | V6: 已匹配
A7: SHOP-00006 | B7: 宠物电动剃毛器 V1 | C7: PET-宠物-0006 | D7: 宠物服饰 | E7: 1 | F7: 有货 | G7: 12.69 | H7: 8.97 | I7: 0 | J7: 0 | K7: =G7+H7+I7+J7 | L7: =$B$3 | M7: =$B$4 | N7: =K7/(1-(L7+M7)) | O7: =ROUND(K7/(1-(L7+M7)),2) | P7: 29.27 | Q7: =IF(N7<P7,"低于亚马逊",IF(N7<P7*1.1,"接近亚马逊","高于亚马逊")) | R7: =ROUND(N7*$B$12,2) | S7: =(O7-N7)/O7 | T7: =(N7-K7)/N7 | U7: =(N7-K7)/N7-$B$4 | V7: 已匹配
A8: SHOP-00007 | B8: 宠物自动喂食器 V1 | C8: PET-宠物-0007 | D8: 宠物美容 | E8: 1 | F8: 有货 | G8: 4.25 | H8: 6.44 | I8: 0 | J8: 0 | K8: =G8+H8+I8+J8 | L8: =$B$3 | M8: =$B$4 | N8: =K8/(1-(L8+M8)) | O8: =ROUND(K8/(1-(L8+M8)),2) | P8: 11.06 | Q8: =IF(N8<P8,"低于亚马逊",IF(N8<P8*1.1,"接近亚马逊","高于亚马逊")) | R8: =ROUND(N8*$B$12,2) | S8: =(O8-N8)/O8 | T8: =(N8-K8)/N8 | U8: =(N8-K8)/N8-$B$4 | V8: 已匹配
A9: SHOP-00008 | B9: 宠物外出牵引绳 V1 | C9: PET-宠物-0008 | D9: 宠物玩具 | E9: 4 | F9: 缺货 | G9: 11.16 | H9: 8.97 | I9: 0 | J9: 0 | K9: =G9+H9+I9+J9 | L9: =$B$3 | M9: =$B$4 | N9: =K9/(1-(L9+M9)) | O9: =ROUND(K9/(1-(L9+M9)),2) | P9: 25.09 | Q9: =IF(N9<P9,"低于亚马逊",IF(N9<P9*1.1,"接近亚马逊","高于亚马逊")) | R9: =ROUND(N9*$B$12,2) | S9: =(O9-N9)/O9 | T9: =(N9-K9)/N9 | U9: =(N9-K9)/N9-$B$4 | V9: 已匹配
A10: SHOP-00009 | B10: 宠物洗澡沐浴露套装 V1 | C10: PET-宠物-0009 | D10: 宠物喂食 | E10: 2 | F10: 有货 | G10: 8.14 | H10: 6.44 | I10: 0 | J10: 0 | K10: =G10+H10+I10+J10 | L10: =$B$3 | M10: =$B$4 | N10: =K10/(1-(L10+M10)) | O10: =ROUND(K10/(1-(L10+M10)),2) | P10: 27.63 | Q10: =IF(N10<P10,"低于亚马逊",IF(N10<P10*1.1,"接近亚马逊","高于亚马逊")) | R10: =ROUND(N10*$B$12,2) | S10: =(O10-N10)/O10 | T10: =(N10-K10)/N10 | U10: =(N10-K10)/N10-$B$4 | V10: 已匹配
A11: SHOP-00010 | B11: 宠物保暖舒适窝 V1 | C11: PET-宠物-0010 | D11: 宠物出行 | E11: 1 | F11: 有货 | G11: 37.38 | H11: 15 | I11: 0 | J11: 0 | K11: =G11+H11+I11+J11 | L11: =$B$3 | M11: =$B$4 | N11: =K11/(1-(L11+M11)) | O11: =ROUND(K11/(1-(L11+M11)),2) | P11: 106.74 | Q11: =IF(N11<P11,"低于亚马逊",IF(N11<P11*1.1,"接近亚马逊","高于亚马逊")) | R11: =ROUND(N11*$B$12,2) | S11: =(O11-N11)/O11 | T11: =(N11-K11)/N11 | U11: =(N11-K11)/N11-$B$4 | V11: 已匹配
A12: SHOP-00011 | B12: 宠物训练响片 V1 | C12: PET-宠物-0011 | D12: 宠物清洁 | E12: 4 | F12: 有货 | G12: 7.28 | H12: 6.44 | I12: 0 | J12: 0 | K12: =G12+H12+I12+J12 | L12: =$B$3 | M12: =$B$4 | N12: =K12/(1-(L12+M12)) | O12: =ROUND(K12/(1-(L12+M12)),2) | P12: 18.22 | Q12: =IF(N12<P12,"低于亚马逊",IF(N12<P12*1.1,"接近亚马逊","高于亚马逊")) | R12: =ROUND(N12*$B$12,2) | S12: =(O12-N12)/O12 | T12: =(N12-K12)/N12 | U12: =(N12-K12)/N12-$B$4 | V12: 已匹配
A13: SHOP-00012 | B13: 宠物拾便器 V1 | C13: PET-宠物-0012 | D13: 宠物服饰 | E13: 3 | F13: 有货 | G13: 5.41 | H13: 6.44 | I13: 0 | J13: 0 | K13: =G13+H13+I13+J13 | L13: =$B$3 | M13: =$B$4 | N13: =K13/(1-(L13+M13)) | O13: =ROUND(K13/(1-(L13+M13)),2) | P13: 15.32 | Q13: =IF(N13<P13,"低于亚马逊",IF(N13<P13*1.1,"接近亚马逊","高于亚马逊")) | R13: =ROUND(N13*$B$12,2) | S13: =(O13-N13)/O13 | T13: =(N13-K13)/N13 | U13: =(N13-K13)/N13-$B$4 | V13: 已匹配
... A181: SHOP-00180 | B181: 宠物眼部护理液 V4 | C181: PET-宠物-0180 | D181: 宠物服饰 | E181: 4 | F181: 缺货 | G181: 24.5 | H181: 8.97 | I181: 0 | J181: 0 | K181: =G181+H181+I181+J181 | L181: =$B$3 | M181: =$B$4 | N181: =K181/(1-(L181+M181)) | O181: =ROUND(K181/(1-(L181+M181)),2) | P181: 66.52 | Q181: =IF(N181<P181,"低于亚马逊",IF(N181<P181*1.1,"接近亚马逊","高于亚马逊")) | R181: =ROUND(N181*$B$12,2) | S181: =(O181-N181)/O181 | T181: =(N181-K181)/N181 | U181: =(N181-K181)/N181-$B$4 | V181: 已匹配

Sheet 汇总分析
A1: 价格调整汇总报告
A3: 统计项目 | B3: 数值
A4: 产品总数 | B4: 180
A5: 平均CJ采购价 | B5: =AVERAGE('产品定价分析表_2026-05-07'!G2:G181)
A6: 平均落地成本 | B6: =AVERAGE('产品定价分析表_2026-05-07'!K2:K181)
A7: 平均零售价 | B7: =AVERAGE('产品定价分析表_2026-05-07'!N2:N181)
A8: 平均毛利率 | B8: =AVERAGE('产品定价分析表_2026-05-07'!U2:U181)
A9: 平均净利率 | B9: =AVERAGE('产品定价分析表_2026-05-07'!V2:V181)
A10: 平均划线价 | B10: =AVERAGE('产品定价分析表_2026-05-07'!O2:O181)
A11: 平均折扣率 | B11: =AVERAGE('产品定价分析表_2026-05-07'!P2:P181)
A13: 价格区间分布
A14: Landed Cost < $10 (小件) | B14: =COUNTIF('产品定价分析表_2026-05-07'!K2:K181,"<10") | C14: =B14/180
A15: $10 <= Landed Cost < $25 (中件) | B15: =COUNTIFS('产品定价分析表_2026-05-07'!K2:K181,">=10",'产品定价分析表_2026-05-07'!K2:K181,"<25") | C15: =B15/180
A16: Landed Cost >= $25 (大件) | B16: =COUNTIF('产品定价分析表_2026-05-07'!K2:K181,">=25") | C16: =B16/180
